{"data":{"__type":{"fields":[{"name":"me","args":[],"type":{"name":"User","kind":"OBJECT","ofType":null}},{"name":"currentUser","args":[],"type":{"name":"WebLoginPayload","kind":"OBJECT","ofType":null}},{"name":"myDevices","args":[],"type":{"name":null,"kind":"NON_NULL","ofType":{"name":null}}},{"name":"users","args":[],"type":{"name":null,"kind":"NON_NULL","ofType":{"name":null}}},{"name":"user","args":[{"name":"id","type":{"name":null}}],"type":{"name":"User","kind":"OBJECT","ofType":null}},{"name":"roleInfo","args":[{"name":"role","type":{"name":null}}],"type":{"name":"RoleInfo","kind":"OBJECT","ofType":null}},{"name":"allRoles","args":[],"type":{"name":null,"kind":"NON_NULL","ofType":{"name":null}}},{"name":"roleHierarchyTree","args":[],"type":{"name":null,"kind":"NON_NULL","ofType":{"name":null}}},{"name":"checkRoleAccess","args":[{"name":"requesterRole","type":{"name":null}},{"name":"targetRole","type":{"name":null}}],"type":{"name":null,"kind":"NON_NULL","ofType":{"name":"RoleAccessCheck"}}},{"name":"checkRolePermission","args":[{"name":"role","type":{"name":null}},{"name":"permission","type":{"name":null}}],"type":{"name":null,"kind":"NON_NULL","ofType":{"name":"RolePermissionCheck"}}},{"name":"getAccessibleRoles","args":[{"name":"requesterRole","type":{"name":null}}],"type":{"name":null,"kind":"NON_NULL","ofType":{"name":null}}},{"name":"getManageableRoles","args":[{"name":"requesterRole","type":{"name":null}}],"type":{"name":null,"kind":"NON_NULL","ofType":{"name":null}}},{"name":"getAssignableRoles","args":[{"name":"requesterRole","type":{"name":null}}],"type":{"name":null,"kind":"NON_NULL","ofType":{"name":null}}},{"name":"getHierarchicalSuperiors","args":[{"name":"role","type":{"name":null}}],"type":{"name":null,"kind":"NON_NULL","ofType":{"name":null}}},{"name":"getHierarchicalSubordinates","args":[{"name":"role","type":{"name":null}}],"type":{"name":null,"kind":"NON_NULL","ofType":{"name":null}}},{"name":"companies","args":[],"type":{"name":null,"kind":"NON_NULL","ofType":{"name":null}}},{"name":"company","args":[{"name":"id","type":{"name":null}}],"type":{"name":"Company","kind":"OBJECT","ofType":null}},{"name":"estates","args":[],"type":{"name":null,"kind":"NON_NULL","ofType":{"name":null}}},{"name":"estate","args":[{"name":"id","type":{"name":null}}],"type":{"name":"Estate","kind":"OBJECT","ofType":null}},{"name":"blocks","args":[],"type":{"name":null,"kind":"NON_NULL","ofType":{"name":null}}},{"name":"block","args":[{"name":"id","type":{"name":null}}],"type":{"name":"Block","kind":"OBJECT","ofType":null}},{"name":"divisions","args":[],"type":{"name":null,"kind":"NON_NULL","ofType":{"name":null}}},{"name":"division","args":[{"name":"id","type":{"name":null}}],"type":{"name":"Division","kind":"OBJECT","ofType":null}},{"name":"myAssignments","args":[],"type":{"name":null,"kind":"NON_NULL","ofType":{"name":"UserAssignments"}}},{"name":"estateAssignments","args":[],"type":{"name":null,"kind":"NON_NULL","ofType":{"name":null}}},{"name":"divisionAssignments","args":[],"type":{"name":null,"kind":"NON_NULL","ofType":{"name":null}}},{"name":"companyAssignments","args":[],"type":{"name":null,"kind":"NON_NULL","ofType":{"name":null}}},{"name":"harvestRecords","args":[],"type":{"name":null,"kind":"NON_NULL","ofType":{"name":null}}},{"name":"harvestRecord","args":[{"name":"id","type":{"name":null}}],"type":{"name":"HarvestRecord","kind":"OBJECT","ofType":null}},{"name":"harvestRecordsByStatus","args":[{"name":"status","type":{"name":null}}],"type":{"name":null,"kind":"NON_NULL","ofType":{"name":null}}},{"name":"gateCheckRecords","args":[],"type":{"name":null,"kind":"NON_NULL","ofType":{"name":null}}},{"name":"gateCheckRecord","args":[{"name":"id","type":{"name":null}}],"type":{"name":"GateCheckRecord","kind":"OBJECT","ofType":null}},{"name":"gateCheckRecordsByStatus","args":[{"name":"status","type":{"name":null}}],"type":{"name":null,"kind":"NON_NULL","ofType":{"name":null}}},{"name":"qrTokens","args":[{"name":"input","type":{"name":"QRTokenQuery"}}],"type":{"name":null,"kind":"NON_NULL","ofType":{"name":null}}},{"name":"validateQRToken","args":[{"name":"token","type":{"name":null}},{"name":"intent","type":{"name":null}}],"type":{"name":null,"kind":"NON_NULL","ofType":{"name":"QRTokenValidation"}}},{"name":"gateCheckSyncRecords","args":[{"name":"input","type":{"name":null}}],"type":{"name":null,"kind":"NON_NULL","ofType":{"name":"GateCheckSyncResponse"}}},{"name":"pendingSyncItems","args":[{"name":"deviceId","type":{"name":null}},{"name":"batchSize","type":{"name":"Int"}}],"type":{"name":null,"kind":"NON_NULL","ofType":{"name":"SyncBatchResponse"}}},{"name":"pksRecords","args":[],"type":{"name":null,"kind":"NON_NULL","ofType":{"name":null}}},{"name":"pksRecord","args":[{"name":"id","type":{"name":null}}],"type":{"name":"PKSRecord","kind":"OBJECT","ofType":null}},{"name":"pksRecordsByQuality","args":[{"name":"kualitas","type":{"name":null}}],"type":{"name":null,"kind":"NON_NULL","ofType":{"name":null}}},{"name":"bjrCalculations","args":[],"type":{"name":null,"kind":"NON_NULL","ofType":{"name":null}}},{"name":"bjrCalculationByPKS","args":[{"name":"pksRecordId","type":{"name":null}}],"type":{"name":"BJRCalculation","kind":"OBJECT","ofType":null}},{"name":"perawatanRecords","args":[],"type":{"name":null,"kind":"NON_NULL","ofType":{"name":null}}},{"name":"perawatanRecord","args":[{"name":"id","type":{"name":null}}],"type":{"name":"PerawatanRecord","kind":"OBJECT","ofType":null}},{"name":"perawatanRecordsByType","args":[{"name":"jenisPerawatan","type":{"name":null}}],"type":{"name":null,"kind":"NON_NULL","ofType":{"name":null}}},{"name":"perawatanRecordsByStatus","args":[{"name":"status","type":{"name":null}}],"type":{"name":null,"kind":"NON_NULL","ofType":{"name":null}}},{"name":"pupukUsageRecords","args":[],"type":{"name":null,"kind":"NON_NULL","ofType":{"name":null}}},{"name":"herbisidaUsageRecords","args":[],"type":{"name":null,"kind":"NON_NULL","ofType":{"name":null}}}]}}}